<?xml version="1.0" encoding="utf-8"?>
<LanguageData>

  <SharedBed.stages.0.label>berbagi tempat tidur</SharedBed.stages.0.label>
  <SharedBed.stages.0.description>Aku harus berbagi tempat tidur dengan orang yang tidak begitu kuinginkan.</SharedBed.stages.0.description>

  <ColonistLeftUnburied.stages.0.label>kolonis belum dimakamkan</ColonistLeftUnburied.stages.0.label>
  <ColonistLeftUnburied.stages.0.description>Salah satu dari kita meninggal dan kita membiarkannya tergeletak begitu saja. Tidak seharusnya ada yang dibiarkan seperti itu. Orang-orang pantas dimakamkan dengan layak.</ColonistLeftUnburied.stages.0.description>

  <Naked.stages.0.label>telanjang</Naked.stages.0.label>
  <Naked.stages.0.description>Aku telanjang. Ini memalukan.</Naked.stages.0.description>

  <Pain.stages.0.label>rasa sakit ringan</Pain.stages.0.label>
  <Pain.stages.0.description>Aww... Itu sakit.</Pain.stages.0.description>
  <Pain.stages.1.label>rasa sakit serius</Pain.stages.1.label>
  <Pain.stages.1.description>Ughhh... Kapan ini akan berakhir?</Pain.stages.1.description>
  <Pain.stages.2.label>rasa sakit hebat</Pain.stages.2.label>
  <Pain.stages.2.description>Hentikan... hentikan... hentikan...</Pain.stages.2.description>
  <Pain.stages.3.label>rasa sakit mengguncang pikiran</Pain.stages.3.label>
  <Pain.stages.3.description>AAAAAHHH!</Pain.stages.3.description>

  <PsychicEmanatorSoothe.stages.0.label>penenang emanator psikis</PsychicEmanatorSoothe.stages.0.label>
  <PsychicEmanatorSoothe.stages.0.description>Emanator psikis membuatku merasa aneh, tapi juga sangat rileks.</PsychicEmanatorSoothe.stages.0.description>

  <PsychicDrone.stages.0.label>penenang psikis</PsychicDrone.stages.0.label>
  <PsychicDrone.stages.0.description>Seperti ada suara menenangkan di belakang pikiranku, menenangkanku, meredakan kegugupanku.</PsychicDrone.stages.0.description>
  <PsychicDrone.stages.1.label>dengung psikis rendah</PsychicDrone.stages.1.label>
  <PsychicDrone.stages.1.description>Seperti ada yang menggaruk di belakang pikiranku. Sebuah suara, berbisik. Aku hanya bisa menangkap beberapa kata, dan aku tidak menyukainya.</PsychicDrone.stages.1.description>
  <PsychicDrone.stages.2.label>dengung psikis sedang</PsychicDrone.stages.2.label>
  <PsychicDrone.stages.2.description>Rasanya seperti ada seseorang yang selalu berada di luar pandangan, berbicara padaku. Suaranya berubah tapi pesannya tidak. Aku seharusnya menyakiti orang. Hentikan ini!</PsychicDrone.stages.2.description>
  <PsychicDrone.stages.3.label>dengung psikis tinggi</PsychicDrone.stages.3.label>
  <PsychicDrone.stages.3.description>Suaranya tak tertahankan keras. Sulit berkonsentrasi. Aku mendapati diriku berbicara balik padanya, berteriak padanya. Tapi ia terus berteriak!</PsychicDrone.stages.3.description>
  <PsychicDrone.stages.4.label>dengung psikis ekstrim</PsychicDrone.stages.4.label>
  <PsychicDrone.stages.4.description>Jantungku berdebar dan aku berkeringat. Yang bisa kupikirkan hanyalah menyakiti dan penderitaan dan semua musuh di sekitarku. Mereka adalah mimpi burukku, mimpi burukku, mimpi burukku...</PsychicDrone.stages.4.description>

  <Joywire.stages.0.label>kawat kesenangan</Joywire.stages.0.label>
  <Joywire.stages.0.description>Rasanya luar biasa.</Joywire.stages.0.description>

  <Aurora.stages.0.label>aurora indah</Aurora.stages.0.label>
  <Aurora.stages.0.description>Pemandangannya menakjubkan.</Aurora.stages.0.description>

  <DoingPassionateWork.stages.0.label>sedikit gairah pada pekerjaanku</DoingPassionateWork.stages.0.label>
  <DoingPassionateWork.stages.0.description>Aku menikmati pekerjaanku.</DoingPassionateWork.stages.0.description>
  <DoingPassionateWork.stages.1.label>gairah membara pada pekerjaanku</DoingPassionateWork.stages.1.label>
  <DoingPassionateWork.stages.1.description>Aku mencintai pekerjaanku. Aku bisa melakukan ini sepanjang hari, setiap hari.</DoingPassionateWork.stages.1.description>

</LanguageData>