<?xml version="1.0" encoding="utf-8"?>
<LanguageData>

  <NegotiationAbility.label>kemampuan negosiasi</NegotiationAbility.label>
  <NegotiationAbility.description>Seberapa efektif orang ini dalam bernegosiasi. Ini mempengaruhi kecepatan merekrut tahanan, dampak terhadap hubungan dengan faksi saat memberi hadiah, dan hasil dari pembicaraan damai.</NegotiationAbility.description>

  <TradePriceImprovement.label>peningkatan harga dagang</TradePriceImprovement.label>
  <TradePriceImprovement.description>Ketika orang ini berperan sebagai negosiator dagang, harga beli dan jual akan membaik sebesar persentase ini.</TradePriceImprovement.description>

  <SocialImpact.label>dampak sosial</SocialImpact.label>
  <SocialImpact.description>Pengali yang menentukan seberapa besar orang lain terpengaruh oleh interaksi sosial dengan orang ini.</SocialImpact.description>

  <!-- Animal -->

  <TameAnimalChance.label>peluang menjinakkan hewan</TameAnimalChance.label>
  <TameAnimalChance.description>Peluang dasar orang ini akan berhasil menjinakkan hewan dalam setiap usaha. Peluang sebenarnya juga dipengaruhi oleh tingkat keliaran hewan. Kegagalan menjinakkan bisa memicu serangan hewan, terutama untuk hewan yang lebih ganas.</TameAnimalChance.description>

  <TrainAnimalChance.label>peluang melatih hewan</TrainAnimalChance.label>
  <TrainAnimalChance.description>Peluang dasar orang ini akan membuat kemajuan dalam melatih hewan dalam satu usaha. Peluang sebenarnya untuk setiap usaha juga akan tergantung pada tingkat keliaran hewan, apakah hewan terikat dengan pelatih, dan sebagainya.</TrainAnimalChance.description>

</LanguageData>