<?xml version="1.0" encoding="utf-8"?>
<LanguageData>

  <WorkToBuild.label>kerja untuk membangun</WorkToBuild.label>
  <WorkToBuild.description>Jumlah dasar kerja yang dibutuhkan untuk membangun struktur, setelah semua bahan terkumpul.</WorkToBuild.description>

  <DoorOpenSpeed.label>kecepatan membuka pintu</DoorOpenSpeed.label>
  <DoorOpenSpeed.description>Kecepatan pintu terbuka. Pintu yang lambat akan memperlambat semua orang yang menggunakannya.</DoorOpenSpeed.description>

  <BedRestEffectiveness.label>efektivitas istirahat</BedRestEffectiveness.label>
  <BedRestEffectiveness.description>Seberapa cepat orang mendapatkan istirahat saat tidur di sini.</BedRestEffectiveness.description>

  <TrapMeleeDamage.label>damage jebakan</TrapMeleeDamage.label>
  <TrapMeleeDamage.description>Berapa banyak damage yang dihasilkan jebakan ini secara rata-rata. Damage sebenarnya akan bervariasi secara acak.</TrapMeleeDamage.description>

  <TrapSpringChance.label>peluang jebakan aktif</TrapSpringChance.label>
  <TrapSpringChance.description>Kemungkinan jebakan akan aktif ketika makhluk yang tidak sadar melewatinya.</TrapSpringChance.description>

  <ResearchSpeedFactor.label>faktor kecepatan penelitian</ResearchSpeedFactor.label>
  <ResearchSpeedFactor.description>Kecepatan orang melakukan penelitian dikalikan dengan nilai ini.</ResearchSpeedFactor.description>
  <ResearchSpeedFactor.parts.1.customLabel>Kebersihan ruangan</ResearchSpeedFactor.parts.1.customLabel>

  <MedicalTendQualityOffset.label>pengaturan kualitas perawatan medis</MedicalTendQualityOffset.label>
  <MedicalTendQualityOffset.description>Kualitas perawatan medis diatur oleh nilai ini.</MedicalTendQualityOffset.description>

  <ImmunityGainSpeedFactor.label>faktor kecepatan mendapat kekebalan</ImmunityGainSpeedFactor.label>
  <ImmunityGainSpeedFactor.description>Kecepatan mendapat kekebalan dikalikan dengan nilai ini.</ImmunityGainSpeedFactor.description>

  <WorkTableWorkSpeedFactor.label>faktor kecepatan kerja</WorkTableWorkSpeedFactor.label>
  <WorkTableWorkSpeedFactor.description>Kecepatan kerja dikalikan dengan nilai ini.</WorkTableWorkSpeedFactor.description>

  <WorkTableEfficiencyFactor.label>faktor efisiensi kerja</WorkTableEfficiencyFactor.label>
  <WorkTableEfficiencyFactor.description>Efisiensi kerja dikalikan dengan nilai ini.</WorkTableEfficiencyFactor.description>

  <JoyGainFactor.label>kekuatan rekreasi</JoyGainFactor.label>
  <JoyGainFactor.description>Seberapa efektif benda ini menghibur orang dan memenuhi kebutuhan rekreasi.</JoyGainFactor.description>

  <SurgerySuccessChanceFactor.label>faktor peluang operasi berhasil</SurgerySuccessChanceFactor.label>
  <SurgerySuccessChanceFactor.description>Pengali untuk peluang operasi akan berhasil jika dilakukan di sini. Peluang keberhasilan operasi juga dipengaruhi oleh banyak faktor lain, termasuk kemampuan dokter bedah dan obat yang digunakan.</SurgerySuccessChanceFactor.description>
  <SurgerySuccessChanceFactor.parts.0.customLabel>Kebersihan ruangan</SurgerySuccessChanceFactor.parts.0.customLabel>

</LanguageData>