<?xml version="1.0" encoding="utf-8"?>
<LanguageData>

  <Cougar.label>puma</Cougar.label>
  <Cougar.labelPlural>puma-puma</Cougar.labelPlural>
  <Cougar.lifeStages.0.label>puma</Cougar.lifeStages.0.label>
  <Cougar.lifeStages.0.labelPlural>puma-puma</Cougar.lifeStages.0.labelPlural>
  <Cougar.lifeStages.0.labelMale>puma jantan</Cougar.lifeStages.0.labelMale>
  <Cougar.lifeStages.0.labelMalePlural>puma-puma jantan</Cougar.lifeStages.0.labelMalePlural>
  <Cougar.lifeStages.0.labelFemale>puma betina</Cougar.lifeStages.0.labelFemale>
  <Cougar.lifeStages.0.labelFemalePlural>puma-puma betina</Cougar.lifeStages.0.labelFemalePlural>
  <Cougar.lifeStages.1.label>puma</Cougar.lifeStages.1.label>
  <Cougar.lifeStages.1.labelPlural>puma-puma</Cougar.lifeStages.1.labelPlural>
  <Cougar.lifeStages.1.labelMale>puma jantan</Cougar.lifeStages.1.labelMale>
  <Cougar.lifeStages.1.labelMalePlural>puma-puma jantan</Cougar.lifeStages.1.labelMalePlural>
  <Cougar.lifeStages.1.labelFemale>puma betina</Cougar.lifeStages.1.labelFemale>
  <Cougar.lifeStages.1.labelFemalePlural>puma-puma betina</Cougar.lifeStages.1.labelFemalePlural>
  <Cougar.lifeStages.2.label>puma</Cougar.lifeStages.2.label>
  <Cougar.lifeStages.2.labelPlural>puma-puma</Cougar.lifeStages.2.labelPlural>
  <Cougar.lifeStages.2.labelMale>puma jantan</Cougar.lifeStages.2.labelMale>
  <Cougar.lifeStages.2.labelMalePlural>puma-puma jantan</Cougar.lifeStages.2.labelMalePlural>
  <Cougar.lifeStages.2.labelFemale>puma betina</Cougar.lifeStages.2.labelFemale>
  <Cougar.lifeStages.2.labelFemalePlural>puma-puma betina</Cougar.lifeStages.2.labelFemalePlural>
  <Cougar.labelMale>puma jantan</Cougar.labelMale>
  <Cougar.labelMalePlural>puma-puma jantan</Cougar.labelMalePlural>
  <Cougar.labelFemale>puma betina</Cougar.labelFemale>
  <Cougar.labelFemalePlural>puma-puma betina</Cougar.labelFemalePlural>

  <Panther.label>panther</Panther.label>
  <Panther.labelPlural>panther-panther</Panther.labelPlural>
  <Panther.lifeStages.0.label>panther</Panther.lifeStages.0.label>
  <Panther.lifeStages.0.labelPlural>panther-panther</Panther.lifeStages.0.labelPlural>
  <Panther.lifeStages.0.labelMale>panther jantan</Panther.lifeStages.0.labelMale>
  <Panther.lifeStages.0.labelMalePlural>panther-panther jantan</Panther.lifeStages.0.labelMalePlural>
  <Panther.lifeStages.0.labelFemale>panther betina</Panther.lifeStages.0.labelFemale>
  <Panther.lifeStages.0.labelFemalePlural>panther-panther betina</Panther.lifeStages.0.labelFemalePlural>
  <Panther.lifeStages.1.label>panther</Panther.lifeStages.1.label>
  <Panther.lifeStages.1.labelPlural>panther-panther</Panther.lifeStages.1.labelPlural>
  <Panther.lifeStages.1.labelMale>panther jantan</Panther.lifeStages.1.labelMale>
  <Panther.lifeStages.1.labelMalePlural>panther-panther jantan</Panther.lifeStages.1.labelMalePlural>
  <Panther.lifeStages.1.labelFemale>panther betina</Panther.lifeStages.1.labelFemale>
  <Panther.lifeStages.1.labelFemalePlural>panther-panther betina</Panther.lifeStages.1.labelFemalePlural>
  <Panther.lifeStages.2.label>panther</Panther.lifeStages.2.label>
  <Panther.lifeStages.2.labelPlural>panther-panther</Panther.lifeStages.2.labelPlural>
  <Panther.lifeStages.2.labelMale>panther jantan</Panther.lifeStages.2.labelMale>
  <Panther.lifeStages.2.labelMalePlural>panther-panther jantan</Panther.lifeStages.2.labelMalePlural>
  <Panther.lifeStages.2.labelFemale>panther betina</Panther.lifeStages.2.labelFemale>
  <Panther.lifeStages.2.labelFemalePlural>panther-panther betina</Panther.lifeStages.2.labelFemalePlural>
  <Panther.labelMale>panther jantan</Panther.labelMale>
  <Panther.labelMalePlural>panther-panther jantan</Panther.labelMalePlural>
  <Panther.labelFemale>panther betina</Panther.labelFemale>
  <Panther.labelFemalePlural>panther-panther betina</Panther.labelFemalePlural>

  <Lynx.label>lynx</Lynx.label>
  <Lynx.labelPlural>lynx-lynx</Lynx.labelPlural>
  <Lynx.lifeStages.0.label>anak lynx</Lynx.lifeStages.0.label>
  <Lynx.lifeStages.0.labelPlural>anak-anak lynx</Lynx.lifeStages.0.labelPlural>
  <Lynx.lifeStages.0.labelMale>anak lynx jantan</Lynx.lifeStages.0.labelMale>
  <Lynx.lifeStages.0.labelMalePlural>anak-anak lynx jantan</Lynx.lifeStages.0.labelMalePlural>
  <Lynx.lifeStages.0.labelFemale>anak lynx betina</Lynx.lifeStages.0.labelFemale>
  <Lynx.lifeStages.0.labelFemalePlural>anak-anak lynx betina</Lynx.lifeStages.0.labelFemalePlural>
  <Lynx.lifeStages.1.label>lynx</Lynx.lifeStages.1.label>
  <Lynx.lifeStages.1.labelPlural>lynx-lynx</Lynx.lifeStages.1.labelPlural>
  <Lynx.lifeStages.1.labelMale>lynx jantan</Lynx.lifeStages.1.labelMale>
  <Lynx.lifeStages.1.labelMalePlural>lynx-lynx jantan</Lynx.lifeStages.1.labelMalePlural>
  <Lynx.lifeStages.1.labelFemale>lynx betina</Lynx.lifeStages.1.labelFemale>
  <Lynx.lifeStages.1.labelFemalePlural>lynx-lynx betina</Lynx.lifeStages.1.labelFemalePlural>
  <Lynx.lifeStages.2.label>lynx</Lynx.lifeStages.2.label>
  <Lynx.lifeStages.2.labelPlural>lynx-lynx</Lynx.lifeStages.2.labelPlural>
  <Lynx.lifeStages.2.labelMale>lynx jantan</Lynx.lifeStages.2.labelMale>
  <Lynx.lifeStages.2.labelMalePlural>lynx-lynx jantan</Lynx.lifeStages.2.labelMalePlural>
  <Lynx.lifeStages.2.labelFemale>lynx betina</Lynx.lifeStages.2.labelFemale>
  <Lynx.lifeStages.2.labelFemalePlural>lynx-lynx betina</Lynx.lifeStages.2.labelFemalePlural>
  <Lynx.labelMale>lynx jantan</Lynx.labelMale>
  <Lynx.labelMalePlural>lynx-lynx jantan</Lynx.labelMalePlural>
  <Lynx.labelFemale>lynx betina</Lynx.labelFemale>
  <Lynx.labelFemalePlural>lynx-lynx betina</Lynx.labelFemalePlural>

</LanguageData>