<?xml version="1.0" encoding="utf-8"?>
<LanguageData>

  <!-- Centipede -->

  <Mech_Centipede.label>sentipede</Mech_Centipede.label>
  <Mech_Centipede.description>Mekanoid tempur berat yang meluncur dengan puluhan kaki kecil. Rangka tebal dan daya tembaknya membuatnya sangat efektif melawan pertahanan statis yang berkelompok. Mereka agak rentan terhadap taktik serang-dan-lari.</Mech_Centipede.description>
  <Mech_Centipede.tools.0.label>kepala</Mech_Centipede.tools.0.label>
  <!-- Flesh Type: Mechanoid -->
  <Mech_Centipede_Corpse.label>bangkai sentipede</Mech_Centipede_Corpse.label>
  <Mech_Centipede_Corpse.description>bangkai sentipede</Mech_Centipede_Corpse.description>


  <!-- Lancer - fast sniper -->

  <Mech_Lancer.label>lanser</Mech_Lancer.label>
  <Mech_Lancer.description>Mekanoid tempur seukuran manusia dengan sensor optik besar di wajahnya untuk membidik senjata dari jarak jauh. Meski efektif pada jarak jauh, ia lebih lemah dalam pertarungan jarak dekat. Veteran perang mekanoid tahu bahwa sering kali, hal paling aman yang dilakukan melawan lanser adalah menyerbu.</Mech_Lancer.description>
  <Mech_Lancer.tools.0.label>tinju kiri</Mech_Lancer.tools.0.label>
  <Mech_Lancer.tools.1.label>tinju kanan</Mech_Lancer.tools.1.label>
  <Mech_Lancer.tools.2.label>kepala</Mech_Lancer.tools.2.label>
  <!-- Flesh Type: Mechanoid -->
  <Mech_Lancer_Corpse.label>bangkai lanser</Mech_Lancer_Corpse.label>
  <Mech_Lancer_Corpse.description>bangkai lanser</Mech_Lancer_Corpse.description>


  <!-- Scyther - fast melee -->

  <Mech_Scyther.label>sabit</Mech_Scyther.label>
  <Mech_Scyther.description>Mekanoid tempur seukuran manusia yang cepat dan ramping, mengkhususkan diri dalam pendekatan cepat dan pertarungan jarak dekat. Tubuh mereka dipenuhi ujung dan pisau tajam, tapi mereka terutama menggunakan dua bilah lengan untuk memotong anggota tubuh atau menguliti korban hidup-hidup.</Mech_Scyther.description>
  <Mech_Scyther.tools.0.label>bilah kiri</Mech_Scyther.tools.0.label>
  <Mech_Scyther.tools.1.label>bilah kanan</Mech_Scyther.tools.1.label>
  <Mech_Scyther.tools.2.label>kepala</Mech_Scyther.tools.2.label>
  <!-- Flesh Type: Mechanoid -->
  <Mech_Scyther_Corpse.label>bangkai sabit</Mech_Scyther_Corpse.label>
  <Mech_Scyther_Corpse.description>bangkai sabit</Mech_Scyther_Corpse.description>


</LanguageData>